kspath/__init__.py
kspath/deviation_path/__init__.py
kspath/deviation_path/mps.py
kspath-0.1.1.dist-info/METADATA
kspath-0.1.1.dist-info/RECORD
kspath-0.1.1.dist-info/WHEEL
kspath-0.1.1.dist-info/top_level.txt
